odoo/addons/product_category_inter_company/README.rst
odoo/addons/product_category_inter_company/__init__.py
odoo/addons/product_category_inter_company/__manifest__.py
odoo/addons/product_category_inter_company/i18n/es.po
odoo/addons/product_category_inter_company/i18n/fr.po
odoo/addons/product_category_inter_company/i18n/product_category_inter_company.pot
odoo/addons/product_category_inter_company/models/__init__.py
odoo/addons/product_category_inter_company/models/product_category.py
odoo/addons/product_category_inter_company/models/product_template.py
odoo/addons/product_category_inter_company/readme/CONTRIBUTORS.rst
odoo/addons/product_category_inter_company/readme/DESCRIPTION.rst
odoo/addons/product_category_inter_company/security/ir_rule.xml
odoo/addons/product_category_inter_company/static/description/icon.png
odoo/addons/product_category_inter_company/static/description/index.html
odoo/addons/product_category_inter_company/tests/__init__.py
odoo/addons/product_category_inter_company/tests/test_product_category.py
odoo/addons/product_category_inter_company/views/product_category.xml
odoo/addons/product_category_inter_company/views/product_template_view.xml
odoo_addon_product_category_inter_company-15.0.1.1.0.6.dist-info/METADATA
odoo_addon_product_category_inter_company-15.0.1.1.0.6.dist-info/WHEEL
odoo_addon_product_category_inter_company-15.0.1.1.0.6.dist-info/top_level.txt
odoo_addon_product_category_inter_company-15.0.1.1.0.6.dist-info/RECORD
