Metadata-Version: 2.1
Name: odoo-addon-product_category_inter_company
Version: 15.0.1.1.0.6
Summary: Product categories as company dependent
Home-page: https://github.com/OCA/multi-company
Author: Akretion, Odoo Community Association (OCA)
Author-email: support@odoo-community.org
License: AGPL-3
Classifier: Programming Language :: Python
Classifier: Framework :: Odoo
Classifier: Framework :: Odoo :: 15.0
Classifier: License :: OSI Approved :: GNU Affero General Public License v3
Requires-Python: >=3.8
Requires-Dist: odoo<15.1dev,>=15.0a
